Workbook

Sheet INSTRUCTIONS
A1: Instructions
A2: SN Rating Input – Instructions
A4: This workbook contains the input data for the SN Rating model.
A5: Each row typically represents one issuer (company) and one time point (t0, optionally t1 for trends).
A6: Use this sheet as a reference for how to structure and populate the input sheets.
A8: GENERAL DO / DON’T
A10: Do
A11: - Use plain numeric values (no % signs, no text) in numeric fields.
A12: - Use the same units as assumed by the model (e.g. ratios in decimals, not %).
A13: - Leave cells blank (empty) where data is missing; do not write 0 unless it is truly zero.
A15: Don’t
A16: - Mix different units in the same column.
... A19: - Use merged cells in data areas.

Sheet metadata
A1: field | B1: value
A2: name | B2: ABC_Sample
A3: country | B3: USA
A4: id | B4: 1234a
A5: sovereign_rating | B5: BBB- | K5: Data Validation Lists (not to be deleted)
A6: sovereign_outlook | B6: Negative | L6: Positive | M6: =+[1]qual_score_scale!$A2 -> 5 | N6: =+[1]score_to_rating!$B2 -> AAA
A7: enable_peer_positioning | B7: TRUE | L7: Stable | M7: =+[1]qual_score_scale!$A3 -> 4 | N7: =+[1]score_to_rating!$B3 -> AA+
A8: enable_hardstops | B8: TRUE | L8: Negative | M8: =+[1]qual_score_scale!$A4 -> 3 | N8: =+[1]score_to_rating!$B4 -> AA
A9: enable_sovereign_cap | B9: TRUE | L9: TRUE | M9: =+[1]qual_score_scale!$A5 -> 2 | N9: =+[1]score_to_rating!$B5 -> AA-
L10: FALSE | M10: =+[1]qual_score_scale!$A6 -> 1 | N10: =+[1]score_to_rating!$B6 -> A+
N11: =+[1]score_to_rating!$B7 -> A
N12: =+[1]score_to_rating!$B8 -> A-
N13: =+[1]score_to_rating!$B9 -> BBB+
N14: =+[1]score_to_rating!$B10 -> BBB
N15: =+[1]score_to_rating!$B11 -> BBB-
N16: =+[1]score_to_rating!$B12 -> BB+
N17: =+[1]score_to_rating!$B13 -> BB
N18: =+[1]score_to_rating!$B14 -> BB-
N19: =+[1]score_to_rating!$B15 -> B+
N20: =+[1]score_to_rating!$B16 -> B
N21: =+[1]score_to_rating!$B17 -> B-
N22: =+[1]score_to_rating!$B18 -> CCC+
... N29: =+[1]score_to_rating!$B25 -> 0

Sheet fin_ratios
A1: metric | B1: weight | C1: FY25 | D1: FY24 | E1: FY23
A2: altman_z | C2: 3 | D2: 2.4 | E2: 1.4
A3: debt_ebitda | B3: 2 | C3: 1.9 | D3: 3.6 | E3: 3.9 | H3: Blank values:
A4: net_debt_ebitda | C4: 1.4 | D4: 3.1 | E4: 3.4 | H4: Blank values on column B would get a default value of 1.
A5: debt_equity | C5: 0.7 | D5: 1.6 | E5: 1.7 | H5: Blank values on column C would result in the ratio being skipped for the model.
A6: debt_capital | C6: 0.4 | D6: 0.57 | E6: 0.6
A7: ffo_debt | C7: 0.8 | D7: 0.17 | E7: 0.16
A8: fcf_debt | C8: 1 | D8: 1.5 | E8: 1.2
A9: interest_coverage | B9: 2 | C9: 2 | D9: 1.2 | E9: 1.5
A10: fixed_charge_coverage | C10: 2 | D10: 1.6 | E10: 1.8
A11: dscr | C11: 0.8 | D11: 1.05 | E11: 1.1
A12: ebitda_margin | C12: 0.1 | D12: 0.165 | E12: 0.155
A13: ebit_margin | C13: 0.09 | D13: 0.11 | E13: 0.1
A14: roa | B14: 2 | C14: 0.06 | D14: 0.052 | E14: 0.05
A15: roe | C15: 0.05 | D15: 0.105 | E15: 0.1
A16: capex_dep | C16: 1.1 | D16: 1.2 | E16: 1.1
A17: current_ratio | C17: 1.1 | D17: 1.2 | E17: 1.1
A18: rollover_coverage | C18: 1.1 | D18: 1.2 | E18: 1.1
A19: quick_ratio | C19: 1.1 | D19: 1.2 | E19: 1.1

Sheet components
A1: metric | B1: FY25 | C1: FY24 | D1: FY23
A2: working_capital | B2: 120 | C2: 110 | D2: 100
A3: total_assets | B3: 1000 | C3: 950 | D3: 900
A4: retained_earnings | B4: 200 | C4: 180 | D4: 160
A5: ebit | B5: 80 | C5: 75 | D5: 70
A6: market_value_equity | B6: 600 | C6: 580 | D6: 550
A7: total_liabilities | B7: 400 | C7: 370 | D7: 350
A8: sales | B8: 900 | C8: 880 | D8: 860

Sheet qual_factors
A1: factor | B1: weight | C1: bucket | D1: FY25 | E1: FY24 | F1: FY23
A2: industry_risk | C2: business_risk | D2: 3 | E2: 3 | F2: 3
A3: market_position | C3: business_risk | D3: 3 | E3: 3 | F3: 3 | H3: Blank values:
A4: revenue_diversification | C4: business_risk | D4: 3 | E4: 3 | F4: 3 | H4: Blank values on column B would get a default value of 1.
A5: revenue_stability | C5: business_risk | D5: 3 | E5: 3 | F5: 3 | H5: Blank values on column C would get a default value of others.
A6: business_model_resilience | C6: business_risk | D6: 3 | E6: 3 | F6: 3 | H6: Blank values on column D would result in the ratio being skipped for the model.
A7: management_quality | C7: management | D7: 3 | E7: 3 | F7: 3
A8: governance | C8: management | D8: 3 | E8: 3 | F8: 3 | H8: 5 | I8: Best
A9: financial_policy | C9: management | D9: 3 | E9: 3 | F9: 3 | H9: 1 | I9: Worst
A10: sovereign_risk | C10: sovereign | D10: 3 | E10: 3 | F10: 3
A11: legal_environment | C11: sovereign | D11: 3 | E11: 3 | F11: 3
A12: transparency | C12: transparency | D12: 3 | E12: 3 | F12: 3

Sheet peers_t0
A1: metric | B1: peer1 | C1: peer2 | D1: peer3 | E1: peer4 | F1: peer5 | G1: peer6 | H1: peer7 | I1: peer8 | J1: peer9
A2: =+fin_ratios!A2 -> altman_z | B2: 1.2 | C2: 1.3 | D2: 1.4 | E2: 1.47 | F2: 1.323 | G2: 1.38915 | H2: 1.250235 | I2: 1.3127468 | J2: 1.1814721
A3: =+fin_ratios!A3 -> debt_ebitda | B3: 2.8 | C3: 3 | D3: 3.1 | E3: 3.255 | F3: 2.9295 | G3: 3.075975 | H3: 2.7683775 | I3: 2.9067964 | J3: 2.6161167
A4: =+fin_ratios!A4 -> net_debt_ebitda | B4: 2.5 | C4: 2.7 | D4: 2.9 | E4: 3.045 | F4: 2.7405 | G4: 2.877525 | H4: 2.5897725 | I4: 2.7192611 | J4: 2.447335
A5: =+fin_ratios!A5 -> debt_equity | B5: 1.3 | C5: 1.4 | D5: 1.5 | E5: 1.575 | F5: 1.4175 | G5: 1.488375 | H5: 1.3395375 | I5: 1.4065144 | J5: 1.2658629
A6: =+fin_ratios!A6 -> debt_capital | B6: 0.5 | C6: 0.52 | D6: 0.54 | E6: 0.567 | F6: 0.5103 | G6: 0.535815 | H6: 0.4822335 | I6: 0.50634518 | J6: 0.45571066
A7: =+fin_ratios!A7 -> ffo_debt | B7: 0.2 | C7: 0.22 | D7: 0.24 | E7: 0.252 | F7: 0.2268 | G7: 0.23814 | H7: 0.214326 | I7: 0.2250423 | J7: 0.20253807
A8: =+fin_ratios!A8 -> fcf_debt | B8: 0.14 | C8: 0.16 | D8: 0.18 | E8: 0.189 | F8: 0.1701 | G8: 0.178605 | H8: 0.1607445 | I8: 0.16878173 | J8: 0.15190355
A9: =+fin_ratios!A9 -> interest_coverage | B9: 2 | C9: 2.5 | D9: 3 | E9: 3.15 | F9: 2.835 | G9: 2.97675 | H9: 2.679075 | I9: 2.8130288 | J9: 2.5317259
A10: =+fin_ratios!A10 -> fixed_charge_coverage | B10: 1.8 | C10: 2 | D10: 2.2 | E10: 2.31 | F10: 2.079 | G10: 2.18295 | H10: 1.964655 | I10: 2.0628878 | J10: 1.856599
A11: =+fin_ratios!A11 -> dscr | B11: 1.2 | C11: 1.3 | D11: 1.4 | E11: 1.47 | F11: 1.323 | G11: 1.38915 | H11: 1.250235 | I11: 1.3127468 | J11: 1.1814721
A12: =+fin_ratios!A12 -> ebitda_margin | B12: 0.17 | C12: 0.18 | D12: 0.19 | E12: 0.1995 | F12: 0.17955 | G12: 0.1885275 | H12: 0.16967475 | I12: 0.17815849 | J12: 0.16034264
A13: =+fin_ratios!A13 -> ebit_margin | B13: 0.115 | C13: 0.125 | D13: 0.13 | E13: 0.1365 | F13: 0.12285 | G13: 0.1289925 | H13: 0.11609325 | I13: 0.12189791 | J13: 0.10970812
... A19: =+fin_ratios!A19 -> quick_ratio | B19: 1.1 | C19: 1.2 | D19: 1.3 | E19: 1.365 | F19: 1.2285 | G19: 1.289925 | H19: 1.1609325 | I19: 1.2189791 | J19: 1.0970812
